edk2_pytool_library-0.23.11.dist-info/licenses/LICENSE
edk2toollib/__init__.py
edk2toollib/gitignore_parser.py
edk2toollib/utility_functions.py
edk2toollib/acpi/__init__.py
edk2toollib/acpi/dmar_parser.py
edk2toollib/acpi/ivrs_parser.py
edk2toollib/bin/__init__.py
edk2toollib/bin/vswhere.exe
edk2toollib/database/__init__.py
edk2toollib/database/edk2_db.py
edk2toollib/database/tables/__init__.py
edk2toollib/database/tables/environment_table.py
edk2toollib/database/tables/inf_table.py
edk2toollib/database/tables/instanced_fv_table.py
edk2toollib/database/tables/instanced_inf_table.py
edk2toollib/database/tables/package_table.py
edk2toollib/database/tables/source_table.py
edk2toollib/log/__init__.py
edk2toollib/log/ansi_handler.py
edk2toollib/log/file_handler.py
edk2toollib/log/junit_report_format.py
edk2toollib/log/string_handler.py
edk2toollib/os/__init__.py
edk2toollib/os/uefivariablesupport.py
edk2toollib/tpm/__init__.py
edk2toollib/tpm/tpm2_defs.py
edk2toollib/tpm/tpm2_policy_calc.py
edk2toollib/tpm/tpm2_simulator.py
edk2toollib/tpm/tpm2_stream.py
edk2toollib/uefi/__init__.py
edk2toollib/uefi/authenticated_variables_structure_support.py
edk2toollib/uefi/bmp_object.py
edk2toollib/uefi/device_path.py
edk2toollib/uefi/fmp_auth_header.py
edk2toollib/uefi/fmp_capsule_header.py
edk2toollib/uefi/pi_firmware_file.py
edk2toollib/uefi/pi_firmware_volume.py
edk2toollib/uefi/status_codes.py
edk2toollib/uefi/uefi_capsule_header.py
edk2toollib/uefi/uefi_multi_phase.py
edk2toollib/uefi/uefi_types.py
edk2toollib/uefi/wincert.py
edk2toollib/uefi/edk2/__init__.py
edk2toollib/uefi/edk2/fmp_payload_header.py
edk2toollib/uefi/edk2/ftw_working_block_format.py
edk2toollib/uefi/edk2/guid_list.py
edk2toollib/uefi/edk2/path_utilities.py
edk2toollib/uefi/edk2/variable_format.py
edk2toollib/uefi/edk2/variable_policy.py
edk2toollib/uefi/edk2/variablestore_manulipulations.py
edk2toollib/uefi/edk2/build_objects/__init__.py
edk2toollib/uefi/edk2/build_objects/dsc.py
edk2toollib/uefi/edk2/build_objects/dsc_translator.py
edk2_pytool_library-0.23.11.dist-info/METADATA
edk2_pytool_library-0.23.11.dist-info/WHEEL
edk2_pytool_library-0.23.11.dist-info/top_level.txt
edk2_pytool_library-0.23.11.dist-info/RECORD
