Metadata-Version: 2.4
Name: edk2-pytool-library
Version: 0.23.11
Summary: Python library supporting UEFI EDK2 firmware development
Maintainer-email: EDK2 Pytool Maintainers <edk2-pytools@microsoft.com>
Project-URL: homepage, https://github.com/tianocore/edk2-pytool-library/
Project-URL: documentation, https://www.tianocore.org/edk2-pytool-library/
Project-URL: issues, https://github.com/tianocore/edk2-pytool-library/issues/
Classifier: Programming Language :: Python :: 3
Classifier: Operating System :: OS Independent
Classifier: Development Status :: 4 - Beta
Classifier: Intended Audience :: Developers
Classifier: Programming Language :: Python :: 3.10
Classifier: Programming Language :: Python :: 3.11
Classifier: Programming Language :: Python :: 3.12
Classifier: Programming Language :: Python :: 3.13
Classifier: Programming Language :: Python :: 3.14
Requires-Python: >=3.10
License-File: LICENSE
Requires-Dist: pyasn1>=0.4.8
Requires-Dist: pyasn1-modules>=0.2.8
Requires-Dist: cryptography>=39.0.1
Requires-Dist: joblib>=1.3.2
Requires-Dist: GitPython>=3.1.30
Requires-Dist: sqlalchemy>=2.0.0
Requires-Dist: pygount>=1.6.1
Requires-Dist: pywin32>=308; sys_platform == "win32"
Provides-Extra: dev
Requires-Dist: ruff==0.14.1; extra == "dev"
Requires-Dist: pytest==8.4.2; extra == "dev"
Requires-Dist: coverage==7.11.0; extra == "dev"
Requires-Dist: pre-commit==4.0.1; extra == "dev"
Provides-Extra: publish
Requires-Dist: setuptools==80.9.0; extra == "publish"
Requires-Dist: build==1.3.0; extra == "publish"
Requires-Dist: twine==6.2.0; extra == "publish"
Provides-Extra: docs
Requires-Dist: black==25.1.0; extra == "docs"
Requires-Dist: mkdocs==1.6.1; extra == "docs"
Requires-Dist: mkdocs-material==9.6.22; extra == "docs"
Requires-Dist: mkdocstrings[python]==0.30.1; extra == "docs"
Requires-Dist: mkdocstrings-python==1.18.2; extra == "docs"
Requires-Dist: markdown-include==0.8.1; extra == "docs"
Requires-Dist: mkdocs-gen-files==0.5.0; extra == "docs"
Requires-Dist: mkdocs-exclude==1.0.2; extra == "docs"
Requires-Dist: mkdocs-awesome-pages-plugin==2.10.1; extra == "docs"
Dynamic: license-file
